{
  "best_metric": 0.40636032819747925,
  "best_model_checkpoint": "distilbert-base-uncased-lora-text-classification\\checkpoint-250",
  "epoch": 2.0,
  "eval_steps": 500,
  "global_step": 500,
  "is_hyper_param_search": false,
  "is_local_process_zero": true,
  "is_world_process_zero": true,
  "log_history": [
    {
      "epoch": 1.0,
      "eval_accuracy": {
        "accuracy": 0.873
      },
      "eval_loss": 0.40636032819747925,
      "eval_runtime": 5.4121,
      "eval_samples_per_second": 184.772,
      "eval_steps_per_second": 46.193,
      "step": 250
    },
    {
      "epoch": 2.0,
      "grad_norm": 9.96055793762207,
      "learning_rate": 0.0008,
      "loss": 0.4415,
      "step": 500
    },
    {
      "epoch": 2.0,
      "eval_accuracy": {
        "accuracy": 0.869
      },
      "eval_loss": 0.45139625668525696,
      "eval_runtime": 5.4494,
      "eval_samples_per_second": 183.507,
      "eval_steps_per_second": 45.877,
      "step": 500
    }
  ],
  "logging_steps": 500,
  "max_steps": 2500,
  "num_input_tokens_seen": 0,
  "num_train_epochs": 10,
  "save_steps": 500,
  "total_flos": 220895304702816.0,
  "train_batch_size": 4,
  "trial_name": null,
  "trial_params": null
}
